diffpy/__init__.py
diffpy/srxconfutils/__init__.py
diffpy/srxconfutils/config.py
diffpy/srxconfutils/configtraits.py
diffpy/srxconfutils/gitarchive.cfg
diffpy/srxconfutils/srxconfutils_app.py
diffpy/srxconfutils/tools.py
diffpy/srxconfutils/version.py
diffpy_srxconfutils-1.0.3.dist-info/licenses/AUTHORS.rst
diffpy_srxconfutils-1.0.3.dist-info/licenses/LICENSE.rst
diffpy_srxconfutils-1.0.3.dist-info/METADATA
diffpy_srxconfutils-1.0.3.dist-info/WHEEL
diffpy_srxconfutils-1.0.3.dist-info/entry_points.txt
diffpy_srxconfutils-1.0.3.dist-info/top_level.txt
diffpy_srxconfutils-1.0.3.dist-info/RECORD
