Metadata-Version: 2.4
Name: diffpy.srxconfutils
Version: 1.0.3
Summary: Configuration utilities for project. Part of xPDFsuite
Author-email: "Simon J.L. Billinge group" <sb2896@columbia.edu>
Maintainer-email: "Simon J.L. Billinge group" <sb2896@columbia.edu>
Project-URL: Homepage, https://github.com/diffpy/diffpy.srxconfutils/
Project-URL: Issues, https://github.com/diffpy/diffpy.srxconfutils/issues/
Keywords: diffpy,pdf,data interpretation
Classifier: Development Status :: 5 - Production/Stable
Classifier: Environment :: Console
Classifier: Intended Audience :: Developers
Classifier: Intended Audience :: Science/Research
Classifier: License :: OSI Approved :: BSD License
Classifier: Operating System :: MacOS :: MacOS X
Classifier: Operating System :: Microsoft :: Windows
Classifier: Operating System :: POSIX
Classifier: Operating System :: Unix
Classifier: Programming Language :: Python :: 3.11
Classifier: Programming Language :: Python :: 3.12
Classifier: Programming Language :: Python :: 3.13
Classifier: Programming Language :: Python :: 3.14
Classifier: Topic :: Scientific/Engineering :: Physics
Classifier: Topic :: Scientific/Engineering :: Chemistry
Requires-Python: <3.15,>=3.11
License-File: LICENSE.rst
License-File: AUTHORS.rst
Requires-Dist: numpy
Requires-Dist: traits
Requires-Dist: traitsui
Dynamic: license-file
